whatsapp/__init__.py
whatsapp/_datastore.py
whatsapp/_types.py
whatsapp/agent_interface.py
whatsapp/conversation.py
whatsapp/conversation_handler.py
whatsapp/events.py
whatsapp/message.py
whatsapp/reply_message.py
whatsapp/utils.py
whatsapp_framework-0.5.0.dist-info/LICENSE
whatsapp_framework-0.5.0.dist-info/METADATA
whatsapp_framework-0.5.0.dist-info/WHEEL
whatsapp_framework-0.5.0.dist-info/RECORD
