Metadata-Version: 2.1
Name: whatsapp-framework
Version: 0.5.0
Summary: Whatsapp framework simplifies building and deploying whatsapp based application
Home-page: https://github.com/raven-consult/whatsapp_framework
Keywords: whatsapp,chatbot
Author: Damian Akpan
Author-email: damiakpan@gmail.com
Requires-Python: >=3.9
Classifier: License :: OSI Approved :: MIT License
Classifier: Programming Language :: Python :: 3
Classifier: Programming Language :: Python :: 3.9
Classifier: Programming Language :: Python :: 3.10
Classifier: Programming Language :: Python :: 3.11
Classifier: Programming Language :: Python :: 3.12
Classifier: Programming Language :: Python :: 3.8
Requires-Dist: google-generativeai (>=0.8.3,<0.9.0)
Requires-Dist: pydantic (>=2.9.1,<3.0.0)
Requires-Dist: pyngrok (>=7.2.0,<8.0.0)
Requires-Dist: requests (>=2.32.3,<3.0.0)
Requires-Dist: werkzeug (>=3.0.4,<4.0.0)
Project-URL: Repository, https://github.com/raven-consult/whatsapp_framework
